MANIFEST.in
setup.cfg
setup.py
django_select_by/__init__.py
django_select_by/widget.py
django_select_by.egg-info/PKG-INFO
django_select_by.egg-info/SOURCES.txt
django_select_by.egg-info/dependency_links.txt
django_select_by.egg-info/not-zip-safe
django_select_by.egg-info/top_level.txt
django_select_by/static/django_select_by.js