Metadata-Version: 1.0
Name: django-select-by
Version: 0.1
Summary: Django lib from select populate by other field
Home-page: https://github.com/DavidLSO/django-select-by
Author: David Levy Sousa Oliveira
Author-email: sdavidlevy@gmail.com
License: MIT License
Platform: UNKNOWN
